MANIFEST.in
setup.py
market_proto/__init__.py
market_proto/intent_pb2.py
market_proto/intent_pb2_grpc.py
market_proto/mongo_pb2.py
market_proto/mongo_pb2_grpc.py
market_proto/redisclient_pb2.py
market_proto/redisclient_pb2_grpc.py
market_proto/ssl_pb2.py
market_proto/ssl_pb2_grpc.py
market_proto/stub_pb2.py
market_proto/stub_pb2_grpc.py
market_proto/vaksana_pb2.py
market_proto/vaksana_pb2_grpc.py
market_proto.egg-info/PKG-INFO
market_proto.egg-info/SOURCES.txt
market_proto.egg-info/dependency_links.txt
market_proto.egg-info/requires.txt
market_proto.egg-info/top_level.txt