Metadata-Version: 1.0
Name: market-proto
Version: 0.1.1.dev0
Summary: SDK to connect to Vaksana Marketplace
Home-page: http://vaksana.com/sdk#python
Author: Pankaj Garg
Author-email: garg.pankaj83@gmail.com
License: PSF
Keywords: Vaksana Market ProtoBuf
Platform: UNKNOWN
